dexguru_sdk/__init__.py
dexguru_sdk/client/__init__.py
dexguru_sdk/client/aiohttp_client.py
dexguru_sdk/client/exceptions.py
dexguru_sdk/models/__init__.py
dexguru_sdk/models/amm_models.py
dexguru_sdk/models/chain_models.py
dexguru_sdk/models/choices.py
dexguru_sdk/models/swaps_burns_mints_models.py
dexguru_sdk/models/token_models.py
dexguru_sdk/models/wallet_models.py
dexguru_sdk/sdk/__init__.py
dexguru_sdk/sdk/dg_sdk.py
dexguru_sdk/utils/__init__.py
dexguru_sdk/utils/get_query.py
tests/__init__.py
tests/test_sdk.py
dexguru_sdk-0.2.8.dist-info/LICENSE
dexguru_sdk-0.2.8.dist-info/METADATA
dexguru_sdk-0.2.8.dist-info/WHEEL
dexguru_sdk-0.2.8.dist-info/top_level.txt
dexguru_sdk-0.2.8.dist-info/RECORD
