Metadata-Version: 2.1
Name: dexguru-sdk
Version: 0.2.8
Home-page: https://dex.guru
License: MIT License
Project-URL: Documentation, https://docs.dex.guru
Project-URL: GitHub, https://github.com/dex-guru/dg-sdk-python
Project-URL: Discord, https://discord.com/invite/dPW8fzwzz9
Classifier: Programming Language :: Python :: 3.7
Classifier: License :: OSI Approved :: MIT License
Classifier: Operating System :: OS Independent
Requires-Python: >=3.7
License-File: LICENSE
Requires-Dist: pydantic (==1.8.2)
Requires-Dist: aiohttp (==3.7.4.post0)
Requires-Dist: ujson (==4.0.2)
